trio_click/__init__.py
trio_click/_bashcomplete.py
trio_click/_compat.py
trio_click/_termui_impl.py
trio_click/_textwrap.py
trio_click/_unicodefun.py
trio_click/_winconsole.py
trio_click/core.py
trio_click/decorators.py
trio_click/exceptions.py
trio_click/formatting.py
trio_click/globals.py
trio_click/parser.py
trio_click/termui.py
trio_click/testing.py
trio_click/types.py
trio_click/utils.py
trio_click-7.0.dev5.dist-info/LICENSE.txt
trio_click-7.0.dev5.dist-info/METADATA
trio_click-7.0.dev5.dist-info/RECORD
trio_click-7.0.dev5.dist-info/WHEEL
trio_click-7.0.dev5.dist-info/top_level.txt
